casabourse/__init__.py
casabourse/__version__.py
casabourse/_legacy_bourse_api.py
casabourse/capitalization.py
casabourse/indices.py
casabourse/instruments.py
casabourse/market.py
casabourse/utils.py
casabourse/volumes.py
casabourse-0.1.5.dist-info/licenses/LICENSE
casabourse-0.1.5.dist-info/METADATA
casabourse-0.1.5.dist-info/WHEEL
casabourse-0.1.5.dist-info/top_level.txt
casabourse-0.1.5.dist-info/RECORD
