Metadata-Version: 2.4
Name: casabourse
Version: 0.1.5
Summary: API Python pour accéder aux données de la Bourse de Casablanca (cours, indices, volumes)
Author-email: Koffi Frederic SESSIE <sessiekoffifrederic@gmail.com>
License: MIT
Project-URL: Homepage, https://github.com/Fredysessie/casabourse
Project-URL: Documentation, https://Fredysessie.github.io/casabourse
Keywords: finance,bourse,maroc,casablanca,trading,stocks
Classifier: Development Status :: 4 - Beta
Classifier: Intended Audience :: Financial and Insurance Industry
Classifier: License :: OSI Approved :: MIT License
Classifier: Operating System :: OS Independent
Classifier: Programming Language :: Python :: 3
Classifier: Programming Language :: Python :: 3.8
Classifier: Topic :: Office/Business :: Financial
Requires-Python: >=3.8
License-File: LICENSE
Requires-Dist: requests>=2.25.0
Requires-Dist: pandas>=1.0.0
Requires-Dist: beautifulsoup4>=4.9.0
Requires-Dist: lxml>=4.6.0
Dynamic: license-file
